Metadata-Version: 2.4
Name: skypilot-kevin
Version: 1.0.0.dev0
Summary: SkyPilot: Run AI on Any Infra — Unified, Faster, Cheaper.
Author: SkyPilot Team
License: Apache 2.0
Project-URL: Homepage, https://github.com/skypilot-org/skypilot
Project-URL: Issues, https://github.com/skypilot-org/skypilot/issues
Project-URL: Discussion, https://github.com/skypilot-org/skypilot/discussions
Project-URL: Documentation, https://docs.skypilot.co/
Classifier: Programming Language :: Python :: 3.7
Classifier: Programming Language :: Python :: 3.8
Classifier: Programming Language :: Python :: 3.9
Classifier: Programming Language :: Python :: 3.10
Classifier: Programming Language :: Python :: 3.11
Classifier: Programming Language :: Python :: 3.12
Classifier: Programming Language :: Python :: 3.13
Classifier: License :: OSI Approved :: Apache Software License
Classifier: Operating System :: OS Independent
Classifier: Topic :: Software Development :: Libraries :: Python Modules
Classifier: Topic :: System :: Distributed Computing
License-File: LICENSE
Requires-Dist: wheel<0.46.0
Requires-Dist: setuptools
Requires-Dist: pip
Requires-Dist: cachetools
Requires-Dist: click<8.2.0,>=7.0
Requires-Dist: colorama
Requires-Dist: cryptography
Requires-Dist: jinja2>=3.0
Requires-Dist: jsonschema
Requires-Dist: networkx
Requires-Dist: pandas>=1.3.0
Requires-Dist: pendulum
Requires-Dist: PrettyTable>=2.0.0
Requires-Dist: python-dotenv
Requires-Dist: rich
Requires-Dist: tabulate
Requires-Dist: typing_extensions
Requires-Dist: filelock>=3.15.0
Requires-Dist: packaging
Requires-Dist: psutil
Requires-Dist: pulp
Requires-Dist: pyyaml!=5.4.*,>3.13
Requires-Dist: requests
Requires-Dist: fastapi
Requires-Dist: uvicorn[standard]
Requires-Dist: pydantic!=2.0.*,!=2.1.*,!=2.2.*,!=2.3.*,!=2.4.*,<3,>2
Requires-Dist: python-multipart
Requires-Dist: aiofiles
Requires-Dist: httpx
Requires-Dist: setproctitle
Requires-Dist: sqlalchemy
Requires-Dist: psycopg2-binary
Requires-Dist: aiosqlite
Requires-Dist: asyncpg
Requires-Dist: casbin
Requires-Dist: sqlalchemy_adapter
Requires-Dist: prometheus_client>=0.8.0
Requires-Dist: passlib
Requires-Dist: bcrypt
Requires-Dist: pyjwt
Requires-Dist: gitpython
Requires-Dist: types-paramiko
Requires-Dist: alembic
Requires-Dist: aiohttp
Requires-Dist: aiosqlite
Requires-Dist: anyio
Provides-Extra: aws
Requires-Dist: awscli>=1.27.10; extra == "aws"
Requires-Dist: botocore>=1.29.10; extra == "aws"
Requires-Dist: boto3>=1.26.1; extra == "aws"
Requires-Dist: colorama<0.4.5; extra == "aws"
Provides-Extra: azure
Requires-Dist: azure-cli>=2.65.0; extra == "azure"
Requires-Dist: azure-core>=1.31.0; extra == "azure"
Requires-Dist: azure-identity>=1.19.0; extra == "azure"
Requires-Dist: azure-mgmt-network>=27.0.0; extra == "azure"
Requires-Dist: azure-mgmt-compute>=33.0.0; extra == "azure"
Requires-Dist: azure-storage-blob>=12.23.1; extra == "azure"
Requires-Dist: msgraph-sdk; extra == "azure"
Requires-Dist: msrestazure; extra == "azure"
Provides-Extra: gcp
Requires-Dist: google-api-python-client>=2.69.0; extra == "gcp"
Requires-Dist: google-cloud-storage; extra == "gcp"
Requires-Dist: pyopenssl<24.3.0,>=23.2.0; extra == "gcp"
Provides-Extra: ibm
Requires-Dist: ibm-cloud-sdk-core; extra == "ibm"
Requires-Dist: ibm-vpc; extra == "ibm"
Requires-Dist: ibm-platform-services>=0.48.0; extra == "ibm"
Requires-Dist: ibm-cos-sdk; extra == "ibm"
Requires-Dist: ray[default]>=2.6.1; extra == "ibm"
Provides-Extra: docker
Requires-Dist: docker; extra == "docker"
Requires-Dist: ray[default]>=2.6.1; extra == "docker"
Provides-Extra: lambda
Provides-Extra: cloudflare
Requires-Dist: awscli>=1.27.10; extra == "cloudflare"
Requires-Dist: botocore>=1.29.10; extra == "cloudflare"
Requires-Dist: boto3>=1.26.1; extra == "cloudflare"
Requires-Dist: colorama<0.4.5; extra == "cloudflare"
Provides-Extra: scp
Requires-Dist: ray[default]>=2.6.1; extra == "scp"
Provides-Extra: oci
Requires-Dist: oci; extra == "oci"
Provides-Extra: kubernetes
Requires-Dist: kubernetes!=32.0.0,>=20.0.0; extra == "kubernetes"
Requires-Dist: websockets; extra == "kubernetes"
Requires-Dist: python-dateutil; extra == "kubernetes"
Provides-Extra: ssh
Requires-Dist: kubernetes!=32.0.0,>=20.0.0; extra == "ssh"
Requires-Dist: websockets; extra == "ssh"
Requires-Dist: python-dateutil; extra == "ssh"
Provides-Extra: remote
Requires-Dist: grpcio>=1.63.0; extra == "remote"
Requires-Dist: protobuf<7.0.0,>=5.26.1; extra == "remote"
Provides-Extra: runpod
Requires-Dist: runpod>=1.6.1; extra == "runpod"
Provides-Extra: fluidstack
Provides-Extra: cudo
Requires-Dist: cudo-compute>=0.1.10; extra == "cudo"
Provides-Extra: paperspace
Provides-Extra: do
Requires-Dist: pydo>=0.3.0; extra == "do"
Requires-Dist: azure-core>=1.24.0; extra == "do"
Requires-Dist: azure-common; extra == "do"
Provides-Extra: vast
Requires-Dist: vastai-sdk>=0.1.12; extra == "vast"
Provides-Extra: vsphere
Requires-Dist: pyvmomi==8.0.1.0.2; extra == "vsphere"
Provides-Extra: nebius
Requires-Dist: nebius>=0.2.47; extra == "nebius"
Requires-Dist: awscli>=1.27.10; extra == "nebius"
Requires-Dist: botocore>=1.29.10; extra == "nebius"
Requires-Dist: boto3>=1.26.1; extra == "nebius"
Requires-Dist: colorama<0.4.5; extra == "nebius"
Provides-Extra: hyperbolic
Provides-Extra: server
Requires-Dist: casbin; extra == "server"
Requires-Dist: sqlalchemy_adapter; extra == "server"
Requires-Dist: passlib; extra == "server"
Requires-Dist: pyjwt; extra == "server"
Requires-Dist: aiohttp; extra == "server"
Requires-Dist: anyio; extra == "server"
Requires-Dist: grpcio>=1.63.0; extra == "server"
Requires-Dist: protobuf<7.0.0,>=5.26.1; extra == "server"
Requires-Dist: aiosqlite; extra == "server"
Provides-Extra: all
Requires-Dist: azure-mgmt-compute>=33.0.0; extra == "all"
Requires-Dist: boto3>=1.26.1; extra == "all"
Requires-Dist: vastai-sdk>=0.1.12; extra == "all"
Requires-Dist: runpod>=1.6.1; extra == "all"
Requires-Dist: ibm-cos-sdk; extra == "all"
Requires-Dist: pyjwt; extra == "all"
Requires-Dist: sqlalchemy_adapter; extra == "all"
Requires-Dist: azure-core>=1.24.0; extra == "all"
Requires-Dist: aiohttp; extra == "all"
Requires-Dist: awscli>=1.27.10; extra == "all"
Requires-Dist: ray[default]>=2.6.1; extra == "all"
Requires-Dist: ibm-platform-services>=0.48.0; extra == "all"
Requires-Dist: azure-cli>=2.65.0; extra == "all"
Requires-Dist: python-dateutil; extra == "all"
Requires-Dist: passlib; extra == "all"
Requires-Dist: msrestazure; extra == "all"
Requires-Dist: oci; extra == "all"
Requires-Dist: docker; extra == "all"
Requires-Dist: kubernetes!=32.0.0,>=20.0.0; extra == "all"
Requires-Dist: azure-core>=1.31.0; extra == "all"
Requires-Dist: anyio; extra == "all"
Requires-Dist: google-cloud-storage; extra == "all"
Requires-Dist: casbin; extra == "all"
Requires-Dist: ibm-vpc; extra == "all"
Requires-Dist: ibm-cloud-sdk-core; extra == "all"
Requires-Dist: azure-mgmt-network>=27.0.0; extra == "all"
Requires-Dist: colorama<0.4.5; extra == "all"
Requires-Dist: pyopenssl<24.3.0,>=23.2.0; extra == "all"
Requires-Dist: msgraph-sdk; extra == "all"
Requires-Dist: grpcio>=1.63.0; extra == "all"
Requires-Dist: websockets; extra == "all"
Requires-Dist: azure-storage-blob>=12.23.1; extra == "all"
Requires-Dist: azure-common; extra == "all"
Requires-Dist: cudo-compute>=0.1.10; extra == "all"
Requires-Dist: protobuf<7.0.0,>=5.26.1; extra == "all"
Requires-Dist: aiosqlite; extra == "all"
Requires-Dist: pydo>=0.3.0; extra == "all"
Requires-Dist: botocore>=1.29.10; extra == "all"
Requires-Dist: google-api-python-client>=2.69.0; extra == "all"
Requires-Dist: pyvmomi==8.0.1.0.2; extra == "all"
Requires-Dist: azure-identity>=1.19.0; extra == "all"
Requires-Dist: nebius>=0.2.47; extra == "all"
Dynamic: author
Dynamic: classifier
Dynamic: description
Dynamic: description-content-type
Dynamic: license
Dynamic: license-file
Dynamic: project-url
Dynamic: provides-extra
Dynamic: requires-dist
Dynamic: summary
